README.txt
setup.cfg
setup.py
ran2/__init__.py
ran2/ran2.py
ran2.egg-info/PKG-INFO
ran2.egg-info/SOURCES.txt
ran2.egg-info/dependency_links.txt
ran2.egg-info/requires.txt
ran2.egg-info/top_level.txt