Metadata-Version: 1.1
Name: ran2
Version: 1.3
Summary: Implements the ran2 function from FORTRAN Numerical Recipes
Home-page: UNKNOWN
Author: Drake Gates
Author-email: dgates8@gmail.com
License: MIT
Keywords: random,number,generator,numerical recipes,rng
Platform: UNKNOWN
Classifier: Topic :: Software Development :: Build Tools
Classifier: License :: OSI Approved :: MIT License
Classifier: Programming Language :: Python :: 3
Classifier: Programming Language :: Python :: 3.4
Classifier: Programming Language :: Python :: 3.5
Classifier: Programming Language :: Python :: 3.6
